Metadata-Version: 1.1
Name: mailsave
Version: 0.8.0
Summary: Dump emails to a file. It can be used as a remplacement for sendmail or an SMTP server.
Home-page: https://gitlab.com/Jenselme/mailsave
Author: Julien Enselme
Author-email: julien.enselme@centrale-marseille.fr
License: MIT
Keywords: mail
Platform: UNKNOWN
Classifier: Programming Language :: Python :: 3
Classifier: Intended Audience :: Developers
Classifier: Intended Audience :: System Administrators
Classifier: License :: OSI Approved :: MIT License
Classifier: Topic :: Communications :: Email
